<profile>

<RTLDesignHierarchy>
<TopModule>
<ModuleName>parse_audio</ModuleName>
<InstancesList>
<Instance>
<InstName>grp_parse_audio_buffer_signal_fu_94</InstName>
<ModuleName>parse_audio_buffer_signal</ModuleName>
<ID>94</ID>
</Instance>
<Instance>
<InstName>grp_parse_audio_buffer_target_fu_102</InstName>
<ModuleName>parse_audio_buffer_target</ModuleName>
<ID>102</ID>
</Instance>
<Instance>
<InstName>grp_parse_audio_parse_signal_fu_84</InstName>
<ModuleName>parse_audio_parse_signal</ModuleName>
<ID>84</ID>
</Instance>
</InstancesList>
</TopModule>
</RTLDesignHierarchy>

<ModuleInformation>
<Module>
<Name>parse_audio_buffer_signal</Name>
<PerformanceEstimates>
<SummaryOfTimingAnalysis>
<TargetClockPeriod>5.00</TargetClockPeriod>
<ClockUncertainty>0.63</ClockUncertainty>
<EstimatedClockPeriod>3.71</EstimatedClockPeriod>
</SummaryOfTimingAnalysis>
<SummaryOfOverallLatency>
<Best-caseLatency>5002</Best-caseLatency>
<Average-caseLatency>5002</Average-caseLatency>
<Worst-caseLatency>5002</Worst-caseLatency>
<PipelineInitiationInterval>5002</PipelineInitiationInterval>
<PipelineType>none</PipelineType>
</SummaryOfOverallLatency>
<SummaryOfLoopLatency>
<Loop1>
<Name>Loop 1</Name>
<TripCount>5000</TripCount>
<Latency>5000</Latency>
<PipelineII>1</PipelineII>
<PipelineDepth>2</PipelineDepth>
</Loop1>
</SummaryOfLoopLatency>
</PerformanceEstimates>
<AreaEstimates>
<Resources>
<FF>35</FF>
<LUT>50</LUT>
<BRAM_18K>0</BRAM_18K>
<DSP48E>0</DSP48E>
</Resources>
</AreaEstimates>
<InterfaceSummary>
<RtlPorts>
<name>ap_clk</name>
<Object>parse_audio_buffer_signal</Object>
<Type>return value</Type>
<Scope></Scope>
<IOProtocol>ap_ctrl_hs</IOProtocol>
<IOConfig></IOConfig>
<Dir>in</Dir>
<Bits>1</Bits>
<Attribute>control</Attribute>
</RtlPorts>
<RtlPorts>
<name>ap_rst</name>
<Object>parse_audio_buffer_signal</Object>
<Type>return value</Type>
<Scope></Scope>
<IOProtocol>ap_ctrl_hs</IOProtocol>
<IOConfig></IOConfig>
<Dir>in</Dir>
<Bits>1</Bits>
<Attribute>control</Attribute>
</RtlPorts>
<RtlPorts>
<name>ap_start</name>
<Object>parse_audio_buffer_signal</Object>
<Type>return value</Type>
<Scope></Scope>
<IOProtocol>ap_ctrl_hs</IOProtocol>
<IOConfig></IOConfig>
<Dir>in</Dir>
<Bits>1</Bits>
<Attribute>control</Attribute>
</RtlPorts>
<RtlPorts>
<name>ap_done</name>
<Object>parse_audio_buffer_signal</Object>
<Type>return value</Type>
<Scope></Scope>
<IOProtocol>ap_ctrl_hs</IOProtocol>
<IOConfig></IOConfig>
<Dir>out</Dir>
<Bits>1</Bits>
<Attribute>control</Attribute>
</RtlPorts>
<RtlPorts>
<name>ap_continue</name>
<Object>parse_audio_buffer_signal</Object>
<Type>return value</Type>
<Scope></Scope>
<IOProtocol>ap_ctrl_hs</IOProtocol>
<IOConfig></IOConfig>
<Dir>in</Dir>
<Bits>1</Bits>
<Attribute>control</Attribute>
</RtlPorts>
<RtlPorts>
<name>ap_idle</name>
<Object>parse_audio_buffer_signal</Object>
<Type>return value</Type>
<Scope></Scope>
<IOProtocol>ap_ctrl_hs</IOProtocol>
<IOConfig></IOConfig>
<Dir>out</Dir>
<Bits>1</Bits>
<Attribute>control</Attribute>
</RtlPorts>
<RtlPorts>
<name>ap_ready</name>
<Object>parse_audio_buffer_signal</Object>
<Type>return value</Type>
<Scope></Scope>
<IOProtocol>ap_ctrl_hs</IOProtocol>
<IOConfig></IOConfig>
<Dir>out</Dir>
<Bits>1</Bits>
<Attribute>control</Attribute>
</RtlPorts>
<RtlPorts>
<name>signals_V_dout</name>
<Object>signals_V</Object>
<Type>pointer</Type>
<Scope></Scope>
<IOProtocol>ap_fifo</IOProtocol>
<IOConfig></IOConfig>
<Dir>in</Dir>
<Bits>32</Bits>
<Attribute>data</Attribute>
</RtlPorts>
<RtlPorts>
<name>signals_V_empty_n</name>
<Object>signals_V</Object>
<Type>pointer</Type>
<Scope></Scope>
<IOProtocol>ap_fifo</IOProtocol>
<IOConfig></IOConfig>
<Dir>in</Dir>
<Bits>1</Bits>
<Attribute>control</Attribute>
</RtlPorts>
<RtlPorts>
<name>signals_V_read</name>
<Object>signals_V</Object>
<Type>pointer</Type>
<Scope></Scope>
<IOProtocol>ap_fifo</IOProtocol>
<IOConfig></IOConfig>
<Dir>out</Dir>
<Bits>1</Bits>
<Attribute>control</Attribute>
</RtlPorts>
<RtlPorts>
<name>amp_buf_address0</name>
<Object>amp_buf</Object>
<Type>array</Type>
<Scope></Scope>
<IOProtocol>ap_memory</IOProtocol>
<IOConfig></IOConfig>
<Dir>out</Dir>
<Bits>14</Bits>
<Attribute>address</Attribute>
</RtlPorts>
<RtlPorts>
<name>amp_buf_ce0</name>
<Object>amp_buf</Object>
<Type>array</Type>
<Scope></Scope>
<IOProtocol>ap_memory</IOProtocol>
<IOConfig></IOConfig>
<Dir>out</Dir>
<Bits>1</Bits>
<Attribute>control</Attribute>
</RtlPorts>
<RtlPorts>
<name>amp_buf_we0</name>
<Object>amp_buf</Object>
<Type>array</Type>
<Scope></Scope>
<IOProtocol>ap_memory</IOProtocol>
<IOConfig></IOConfig>
<Dir>out</Dir>
<Bits>1</Bits>
<Attribute>control</Attribute>
</RtlPorts>
<RtlPorts>
<name>amp_buf_d0</name>
<Object>amp_buf</Object>
<Type>array</Type>
<Scope></Scope>
<IOProtocol>ap_memory</IOProtocol>
<IOConfig></IOConfig>
<Dir>out</Dir>
<Bits>32</Bits>
<Attribute>data</Attribute>
</RtlPorts>
</InterfaceSummary>
</Module>
<Module>
<Name>parse_audio_buffer_target</Name>
<PerformanceEstimates>
<SummaryOfTimingAnalysis>
<TargetClockPeriod>5.00</TargetClockPeriod>
<ClockUncertainty>0.63</ClockUncertainty>
<EstimatedClockPeriod>3.39</EstimatedClockPeriod>
</SummaryOfTimingAnalysis>
<SummaryOfOverallLatency>
<Best-caseLatency>14</Best-caseLatency>
<Average-caseLatency>14</Average-caseLatency>
<Worst-caseLatency>14</Worst-caseLatency>
<PipelineInitiationInterval>14</PipelineInitiationInterval>
<PipelineType>none</PipelineType>
</SummaryOfOverallLatency>
<SummaryOfLoopLatency>
<Loop1>
<Name>Loop 1</Name>
<TripCount>12</TripCount>
<Latency>12</Latency>
<PipelineII>1</PipelineII>
<PipelineDepth>2</PipelineDepth>
</Loop1>
</SummaryOfLoopLatency>
</PerformanceEstimates>
<AreaEstimates>
<Resources>
<FF>15</FF>
<LUT>17</LUT>
<BRAM_18K>0</BRAM_18K>
<DSP48E>0</DSP48E>
</Resources>
</AreaEstimates>
<InterfaceSummary>
<RtlPorts>
<name>ap_clk</name>
<Object>parse_audio_buffer_target</Object>
<Type>return value</Type>
<Scope></Scope>
<IOProtocol>ap_ctrl_hs</IOProtocol>
<IOConfig></IOConfig>
<Dir>in</Dir>
<Bits>1</Bits>
<Attribute>control</Attribute>
</RtlPorts>
<RtlPorts>
<name>ap_rst</name>
<Object>parse_audio_buffer_target</Object>
<Type>return value</Type>
<Scope></Scope>
<IOProtocol>ap_ctrl_hs</IOProtocol>
<IOConfig></IOConfig>
<Dir>in</Dir>
<Bits>1</Bits>
<Attribute>control</Attribute>
</RtlPorts>
<RtlPorts>
<name>ap_start</name>
<Object>parse_audio_buffer_target</Object>
<Type>return value</Type>
<Scope></Scope>
<IOProtocol>ap_ctrl_hs</IOProtocol>
<IOConfig></IOConfig>
<Dir>in</Dir>
<Bits>1</Bits>
<Attribute>control</Attribute>
</RtlPorts>
<RtlPorts>
<name>ap_done</name>
<Object>parse_audio_buffer_target</Object>
<Type>return value</Type>
<Scope></Scope>
<IOProtocol>ap_ctrl_hs</IOProtocol>
<IOConfig></IOConfig>
<Dir>out</Dir>
<Bits>1</Bits>
<Attribute>control</Attribute>
</RtlPorts>
<RtlPorts>
<name>ap_continue</name>
<Object>parse_audio_buffer_target</Object>
<Type>return value</Type>
<Scope></Scope>
<IOProtocol>ap_ctrl_hs</IOProtocol>
<IOConfig></IOConfig>
<Dir>in</Dir>
<Bits>1</Bits>
<Attribute>control</Attribute>
</RtlPorts>
<RtlPorts>
<name>ap_idle</name>
<Object>parse_audio_buffer_target</Object>
<Type>return value</Type>
<Scope></Scope>
<IOProtocol>ap_ctrl_hs</IOProtocol>
<IOConfig></IOConfig>
<Dir>out</Dir>
<Bits>1</Bits>
<Attribute>control</Attribute>
</RtlPorts>
<RtlPorts>
<name>ap_ready</name>
<Object>parse_audio_buffer_target</Object>
<Type>return value</Type>
<Scope></Scope>
<IOProtocol>ap_ctrl_hs</IOProtocol>
<IOConfig></IOConfig>
<Dir>out</Dir>
<Bits>1</Bits>
<Attribute>control</Attribute>
</RtlPorts>
<RtlPorts>
<name>hits_V_dout</name>
<Object>hits_V</Object>
<Type>pointer</Type>
<Scope></Scope>
<IOProtocol>ap_fifo</IOProtocol>
<IOConfig></IOConfig>
<Dir>in</Dir>
<Bits>32</Bits>
<Attribute>data</Attribute>
</RtlPorts>
<RtlPorts>
<name>hits_V_empty_n</name>
<Object>hits_V</Object>
<Type>pointer</Type>
<Scope></Scope>
<IOProtocol>ap_fifo</IOProtocol>
<IOConfig></IOConfig>
<Dir>in</Dir>
<Bits>1</Bits>
<Attribute>control</Attribute>
</RtlPorts>
<RtlPorts>
<name>hits_V_read</name>
<Object>hits_V</Object>
<Type>pointer</Type>
<Scope></Scope>
<IOProtocol>ap_fifo</IOProtocol>
<IOConfig></IOConfig>
<Dir>out</Dir>
<Bits>1</Bits>
<Attribute>control</Attribute>
</RtlPorts>
<RtlPorts>
<name>locs_V_dout</name>
<Object>locs_V</Object>
<Type>pointer</Type>
<Scope></Scope>
<IOProtocol>ap_fifo</IOProtocol>
<IOConfig></IOConfig>
<Dir>in</Dir>
<Bits>32</Bits>
<Attribute>data</Attribute>
</RtlPorts>
<RtlPorts>
<name>locs_V_empty_n</name>
<Object>locs_V</Object>
<Type>pointer</Type>
<Scope></Scope>
<IOProtocol>ap_fifo</IOProtocol>
<IOConfig></IOConfig>
<Dir>in</Dir>
<Bits>1</Bits>
<Attribute>control</Attribute>
</RtlPorts>
<RtlPorts>
<name>locs_V_read</name>
<Object>locs_V</Object>
<Type>pointer</Type>
<Scope></Scope>
<IOProtocol>ap_fifo</IOProtocol>
<IOConfig></IOConfig>
<Dir>out</Dir>
<Bits>1</Bits>
<Attribute>control</Attribute>
</RtlPorts>
<RtlPorts>
<name>loc_buf_address0</name>
<Object>loc_buf</Object>
<Type>array</Type>
<Scope></Scope>
<IOProtocol>ap_memory</IOProtocol>
<IOConfig></IOConfig>
<Dir>out</Dir>
<Bits>4</Bits>
<Attribute>address</Attribute>
</RtlPorts>
<RtlPorts>
<name>loc_buf_ce0</name>
<Object>loc_buf</Object>
<Type>array</Type>
<Scope></Scope>
<IOProtocol>ap_memory</IOProtocol>
<IOConfig></IOConfig>
<Dir>out</Dir>
<Bits>1</Bits>
<Attribute>control</Attribute>
</RtlPorts>
<RtlPorts>
<name>loc_buf_we0</name>
<Object>loc_buf</Object>
<Type>array</Type>
<Scope></Scope>
<IOProtocol>ap_memory</IOProtocol>
<IOConfig></IOConfig>
<Dir>out</Dir>
<Bits>1</Bits>
<Attribute>control</Attribute>
</RtlPorts>
<RtlPorts>
<name>loc_buf_d0</name>
<Object>loc_buf</Object>
<Type>array</Type>
<Scope></Scope>
<IOProtocol>ap_memory</IOProtocol>
<IOConfig></IOConfig>
<Dir>out</Dir>
<Bits>32</Bits>
<Attribute>data</Attribute>
</RtlPorts>
</InterfaceSummary>
</Module>
<Module>
<Name>parse_audio_parse_signal</Name>
<PerformanceEstimates>
<SummaryOfTimingAnalysis>
<TargetClockPeriod>5.00</TargetClockPeriod>
<ClockUncertainty>0.63</ClockUncertainty>
<EstimatedClockPeriod>3.94</EstimatedClockPeriod>
</SummaryOfTimingAnalysis>
<SummaryOfOverallLatency>
<Best-caseLatency>109</Best-caseLatency>
<Average-caseLatency>undef</Average-caseLatency>
<Worst-caseLatency>21625</Worst-caseLatency>
<PipelineInitiationInterval>109 ~ 21625</PipelineInitiationInterval>
<PipelineType>none</PipelineType>
</SummaryOfOverallLatency>
<SummaryOfLoopLatency>
<Loop1>
<Name>Loop 1</Name>
<TripCount>12</TripCount>
<Latency>108 ~ 21624</Latency>
<IterationLatency>
<range>
<min>9</min>
<max>1802</max>
</range>
</IterationLatency>
<PipelineDepth>9 ~ 1802</PipelineDepth>
<Loop1.1>
<Name>Loop 1.1</Name>
<TripCount>
<range>
<min>1</min>
<max>12</max>
</range>
</TripCount>
<Latency>7 ~ 1800</Latency>
<IterationLatency>
<range>
<min>7</min>
<max>150</max>
</range>
</IterationLatency>
<PipelineDepth>7 ~ 150</PipelineDepth>
<Loop1.1.1>
<Name>Loop 1.1.1</Name>
<TripCount>
<range>
<min>1</min>
<max>144</max>
</range>
</TripCount>
<Latency>1 ~ 144</Latency>
<PipelineII>1</PipelineII>
<PipelineDepth>2</PipelineDepth>
</Loop1.1.1>
</Loop1.1>
</Loop1>
</SummaryOfLoopLatency>
</PerformanceEstimates>
<AreaEstimates>
<Resources>
<FF>185</FF>
<LUT>241</LUT>
<BRAM_18K>0</BRAM_18K>
<DSP48E>0</DSP48E>
</Resources>
</AreaEstimates>
<InterfaceSummary>
<RtlPorts>
<name>ap_clk</name>
<Object>parse_audio_parse_signal</Object>
<Type>return value</Type>
<Scope></Scope>
<IOProtocol>ap_ctrl_hs</IOProtocol>
<IOConfig></IOConfig>
<Dir>in</Dir>
<Bits>1</Bits>
<Attribute>control</Attribute>
</RtlPorts>
<RtlPorts>
<name>ap_rst</name>
<Object>parse_audio_parse_signal</Object>
<Type>return value</Type>
<Scope></Scope>
<IOProtocol>ap_ctrl_hs</IOProtocol>
<IOConfig></IOConfig>
<Dir>in</Dir>
<Bits>1</Bits>
<Attribute>control</Attribute>
</RtlPorts>
<RtlPorts>
<name>ap_start</name>
<Object>parse_audio_parse_signal</Object>
<Type>return value</Type>
<Scope></Scope>
<IOProtocol>ap_ctrl_hs</IOProtocol>
<IOConfig></IOConfig>
<Dir>in</Dir>
<Bits>1</Bits>
<Attribute>control</Attribute>
</RtlPorts>
<RtlPorts>
<name>ap_done</name>
<Object>parse_audio_parse_signal</Object>
<Type>return value</Type>
<Scope></Scope>
<IOProtocol>ap_ctrl_hs</IOProtocol>
<IOConfig></IOConfig>
<Dir>out</Dir>
<Bits>1</Bits>
<Attribute>control</Attribute>
</RtlPorts>
<RtlPorts>
<name>ap_continue</name>
<Object>parse_audio_parse_signal</Object>
<Type>return value</Type>
<Scope></Scope>
<IOProtocol>ap_ctrl_hs</IOProtocol>
<IOConfig></IOConfig>
<Dir>in</Dir>
<Bits>1</Bits>
<Attribute>control</Attribute>
</RtlPorts>
<RtlPorts>
<name>ap_idle</name>
<Object>parse_audio_parse_signal</Object>
<Type>return value</Type>
<Scope></Scope>
<IOProtocol>ap_ctrl_hs</IOProtocol>
<IOConfig></IOConfig>
<Dir>out</Dir>
<Bits>1</Bits>
<Attribute>control</Attribute>
</RtlPorts>
<RtlPorts>
<name>ap_ready</name>
<Object>parse_audio_parse_signal</Object>
<Type>return value</Type>
<Scope></Scope>
<IOProtocol>ap_ctrl_hs</IOProtocol>
<IOConfig></IOConfig>
<Dir>out</Dir>
<Bits>1</Bits>
<Attribute>control</Attribute>
</RtlPorts>
<RtlPorts>
<name>signal_r_address0</name>
<Object>signal_r</Object>
<Type>array</Type>
<Scope></Scope>
<IOProtocol>ap_memory</IOProtocol>
<IOConfig></IOConfig>
<Dir>out</Dir>
<Bits>14</Bits>
<Attribute>address</Attribute>
</RtlPorts>
<RtlPorts>
<name>signal_r_ce0</name>
<Object>signal_r</Object>
<Type>array</Type>
<Scope></Scope>
<IOProtocol>ap_memory</IOProtocol>
<IOConfig></IOConfig>
<Dir>out</Dir>
<Bits>1</Bits>
<Attribute>control</Attribute>
</RtlPorts>
<RtlPorts>
<name>signal_r_q0</name>
<Object>signal_r</Object>
<Type>array</Type>
<Scope></Scope>
<IOProtocol>ap_memory</IOProtocol>
<IOConfig></IOConfig>
<Dir>in</Dir>
<Bits>32</Bits>
<Attribute>data</Attribute>
</RtlPorts>
<RtlPorts>
<name>locs_address0</name>
<Object>locs</Object>
<Type>array</Type>
<Scope></Scope>
<IOProtocol>ap_memory</IOProtocol>
<IOConfig></IOConfig>
<Dir>out</Dir>
<Bits>4</Bits>
<Attribute>address</Attribute>
</RtlPorts>
<RtlPorts>
<name>locs_ce0</name>
<Object>locs</Object>
<Type>array</Type>
<Scope></Scope>
<IOProtocol>ap_memory</IOProtocol>
<IOConfig></IOConfig>
<Dir>out</Dir>
<Bits>1</Bits>
<Attribute>control</Attribute>
</RtlPorts>
<RtlPorts>
<name>locs_q0</name>
<Object>locs</Object>
<Type>array</Type>
<Scope></Scope>
<IOProtocol>ap_memory</IOProtocol>
<IOConfig></IOConfig>
<Dir>in</Dir>
<Bits>32</Bits>
<Attribute>data</Attribute>
</RtlPorts>
<RtlPorts>
<name>locs_address1</name>
<Object>locs</Object>
<Type>array</Type>
<Scope></Scope>
<IOProtocol>ap_memory</IOProtocol>
<IOConfig></IOConfig>
<Dir>out</Dir>
<Bits>4</Bits>
<Attribute>address</Attribute>
</RtlPorts>
<RtlPorts>
<name>locs_ce1</name>
<Object>locs</Object>
<Type>array</Type>
<Scope></Scope>
<IOProtocol>ap_memory</IOProtocol>
<IOConfig></IOConfig>
<Dir>out</Dir>
<Bits>1</Bits>
<Attribute>control</Attribute>
</RtlPorts>
<RtlPorts>
<name>locs_q1</name>
<Object>locs</Object>
<Type>array</Type>
<Scope></Scope>
<IOProtocol>ap_memory</IOProtocol>
<IOConfig></IOConfig>
<Dir>in</Dir>
<Bits>32</Bits>
<Attribute>data</Attribute>
</RtlPorts>
<RtlPorts>
<name>pairs_amplitude_V_din</name>
<Object>pairs_amplitude_V</Object>
<Type>pointer</Type>
<Scope></Scope>
<IOProtocol>ap_fifo</IOProtocol>
<IOConfig></IOConfig>
<Dir>out</Dir>
<Bits>32</Bits>
<Attribute>data</Attribute>
</RtlPorts>
<RtlPorts>
<name>pairs_amplitude_V_full_n</name>
<Object>pairs_amplitude_V</Object>
<Type>pointer</Type>
<Scope></Scope>
<IOProtocol>ap_fifo</IOProtocol>
<IOConfig></IOConfig>
<Dir>in</Dir>
<Bits>1</Bits>
<Attribute>control</Attribute>
</RtlPorts>
<RtlPorts>
<name>pairs_amplitude_V_write</name>
<Object>pairs_amplitude_V</Object>
<Type>pointer</Type>
<Scope></Scope>
<IOProtocol>ap_fifo</IOProtocol>
<IOConfig></IOConfig>
<Dir>out</Dir>
<Bits>1</Bits>
<Attribute>control</Attribute>
</RtlPorts>
<RtlPorts>
<name>pairs_duration_V_din</name>
<Object>pairs_duration_V</Object>
<Type>pointer</Type>
<Scope></Scope>
<IOProtocol>ap_fifo</IOProtocol>
<IOConfig></IOConfig>
<Dir>out</Dir>
<Bits>32</Bits>
<Attribute>data</Attribute>
</RtlPorts>
<RtlPorts>
<name>pairs_duration_V_full_n</name>
<Object>pairs_duration_V</Object>
<Type>pointer</Type>
<Scope></Scope>
<IOProtocol>ap_fifo</IOProtocol>
<IOConfig></IOConfig>
<Dir>in</Dir>
<Bits>1</Bits>
<Attribute>control</Attribute>
</RtlPorts>
<RtlPorts>
<name>pairs_duration_V_write</name>
<Object>pairs_duration_V</Object>
<Type>pointer</Type>
<Scope></Scope>
<IOProtocol>ap_fifo</IOProtocol>
<IOConfig></IOConfig>
<Dir>out</Dir>
<Bits>1</Bits>
<Attribute>control</Attribute>
</RtlPorts>
</InterfaceSummary>
</Module>
<Module>
<Name>parse_audio</Name>
<PerformanceEstimates>
<SummaryOfTimingAnalysis>
<TargetClockPeriod>5.00</TargetClockPeriod>
<ClockUncertainty>0.63</ClockUncertainty>
<EstimatedClockPeriod>3.94</EstimatedClockPeriod>
</SummaryOfTimingAnalysis>
<SummaryOfOverallLatency>
<Best-caseLatency>5112</Best-caseLatency>
<Average-caseLatency>undef</Average-caseLatency>
<Worst-caseLatency>26628</Worst-caseLatency>
<DataflowPipelineThroughput>
<range>
<min>5003</min>
<max>21626</max>
</range>
</DataflowPipelineThroughput>
<PipelineInitiationInterval>5003 ~ 21626</PipelineInitiationInterval>
<PipelineType>dataflow</PipelineType>
</SummaryOfOverallLatency>
</PerformanceEstimates>
<AreaEstimates>
<Resources>
<BRAM_18K>64</BRAM_18K>
<FF>369</FF>
<LUT>323</LUT>
<DSP48E>0</DSP48E>
</Resources>
</AreaEstimates>
<InterfaceSummary>
<RtlPorts>
<name>ap_clk</name>
<Object>parse_audio</Object>
<Type>return value</Type>
<Scope></Scope>
<IOProtocol>ap_ctrl_hs</IOProtocol>
<IOConfig></IOConfig>
<Dir>in</Dir>
<Bits>1</Bits>
<Attribute>control</Attribute>
</RtlPorts>
<RtlPorts>
<name>ap_rst</name>
<Object>parse_audio</Object>
<Type>return value</Type>
<Scope></Scope>
<IOProtocol>ap_ctrl_hs</IOProtocol>
<IOConfig></IOConfig>
<Dir>in</Dir>
<Bits>1</Bits>
<Attribute>control</Attribute>
</RtlPorts>
<RtlPorts>
<name>ap_done</name>
<Object>parse_audio</Object>
<Type>return value</Type>
<Scope></Scope>
<IOProtocol>ap_ctrl_hs</IOProtocol>
<IOConfig></IOConfig>
<Dir>out</Dir>
<Bits>1</Bits>
<Attribute>control</Attribute>
</RtlPorts>
<RtlPorts>
<name>ap_start</name>
<Object>parse_audio</Object>
<Type>return value</Type>
<Scope></Scope>
<IOProtocol>ap_ctrl_hs</IOProtocol>
<IOConfig></IOConfig>
<Dir>in</Dir>
<Bits>1</Bits>
<Attribute>control</Attribute>
</RtlPorts>
<RtlPorts>
<name>ap_idle</name>
<Object>parse_audio</Object>
<Type>return value</Type>
<Scope></Scope>
<IOProtocol>ap_ctrl_hs</IOProtocol>
<IOConfig></IOConfig>
<Dir>out</Dir>
<Bits>1</Bits>
<Attribute>control</Attribute>
</RtlPorts>
<RtlPorts>
<name>ap_ready</name>
<Object>parse_audio</Object>
<Type>return value</Type>
<Scope></Scope>
<IOProtocol>ap_ctrl_hs</IOProtocol>
<IOConfig></IOConfig>
<Dir>out</Dir>
<Bits>1</Bits>
<Attribute>control</Attribute>
</RtlPorts>
<RtlPorts>
<name>signals_V_dout</name>
<Object>signals_V</Object>
<Type>pointer</Type>
<Scope></Scope>
<IOProtocol>ap_fifo</IOProtocol>
<IOConfig></IOConfig>
<Dir>in</Dir>
<Bits>32</Bits>
<Attribute>data</Attribute>
<CType>float</CType>
</RtlPorts>
<RtlPorts>
<name>signals_V_empty_n</name>
<Object>signals_V</Object>
<Type>pointer</Type>
<Scope></Scope>
<IOProtocol>ap_fifo</IOProtocol>
<IOConfig></IOConfig>
<Dir>in</Dir>
<Bits>1</Bits>
<Attribute>control</Attribute>
<CType>float</CType>
</RtlPorts>
<RtlPorts>
<name>signals_V_read</name>
<Object>signals_V</Object>
<Type>pointer</Type>
<Scope></Scope>
<IOProtocol>ap_fifo</IOProtocol>
<IOConfig></IOConfig>
<Dir>out</Dir>
<Bits>1</Bits>
<Attribute>control</Attribute>
<CType>float</CType>
</RtlPorts>
<RtlPorts>
<name>hits_V_dout</name>
<Object>hits_V</Object>
<Type>pointer</Type>
<Scope></Scope>
<IOProtocol>ap_fifo</IOProtocol>
<IOConfig></IOConfig>
<Dir>in</Dir>
<Bits>32</Bits>
<Attribute>data</Attribute>
<CType>float</CType>
</RtlPorts>
<RtlPorts>
<name>hits_V_empty_n</name>
<Object>hits_V</Object>
<Type>pointer</Type>
<Scope></Scope>
<IOProtocol>ap_fifo</IOProtocol>
<IOConfig></IOConfig>
<Dir>in</Dir>
<Bits>1</Bits>
<Attribute>control</Attribute>
<CType>float</CType>
</RtlPorts>
<RtlPorts>
<name>hits_V_read</name>
<Object>hits_V</Object>
<Type>pointer</Type>
<Scope></Scope>
<IOProtocol>ap_fifo</IOProtocol>
<IOConfig></IOConfig>
<Dir>out</Dir>
<Bits>1</Bits>
<Attribute>control</Attribute>
<CType>float</CType>
</RtlPorts>
<RtlPorts>
<name>locs_V_dout</name>
<Object>locs_V</Object>
<Type>pointer</Type>
<Scope></Scope>
<IOProtocol>ap_fifo</IOProtocol>
<IOConfig></IOConfig>
<Dir>in</Dir>
<Bits>32</Bits>
<Attribute>data</Attribute>
<CType>int</CType>
</RtlPorts>
<RtlPorts>
<name>locs_V_empty_n</name>
<Object>locs_V</Object>
<Type>pointer</Type>
<Scope></Scope>
<IOProtocol>ap_fifo</IOProtocol>
<IOConfig></IOConfig>
<Dir>in</Dir>
<Bits>1</Bits>
<Attribute>control</Attribute>
<CType>int</CType>
</RtlPorts>
<RtlPorts>
<name>locs_V_read</name>
<Object>locs_V</Object>
<Type>pointer</Type>
<Scope></Scope>
<IOProtocol>ap_fifo</IOProtocol>
<IOConfig></IOConfig>
<Dir>out</Dir>
<Bits>1</Bits>
<Attribute>control</Attribute>
<CType>int</CType>
</RtlPorts>
<RtlPorts>
<name>pairs_amplitude_V_din</name>
<Object>pairs_amplitude_V</Object>
<Type>pointer</Type>
<Scope></Scope>
<IOProtocol>ap_fifo</IOProtocol>
<IOConfig></IOConfig>
<Dir>out</Dir>
<Bits>32</Bits>
<Attribute>data</Attribute>
<CType>float</CType>
</RtlPorts>
<RtlPorts>
<name>pairs_amplitude_V_full_n</name>
<Object>pairs_amplitude_V</Object>
<Type>pointer</Type>
<Scope></Scope>
<IOProtocol>ap_fifo</IOProtocol>
<IOConfig></IOConfig>
<Dir>in</Dir>
<Bits>1</Bits>
<Attribute>control</Attribute>
<CType>float</CType>
</RtlPorts>
<RtlPorts>
<name>pairs_amplitude_V_write</name>
<Object>pairs_amplitude_V</Object>
<Type>pointer</Type>
<Scope></Scope>
<IOProtocol>ap_fifo</IOProtocol>
<IOConfig></IOConfig>
<Dir>out</Dir>
<Bits>1</Bits>
<Attribute>control</Attribute>
<CType>float</CType>
</RtlPorts>
<RtlPorts>
<name>pairs_duration_V_din</name>
<Object>pairs_duration_V</Object>
<Type>pointer</Type>
<Scope></Scope>
<IOProtocol>ap_fifo</IOProtocol>
<IOConfig></IOConfig>
<Dir>out</Dir>
<Bits>32</Bits>
<Attribute>data</Attribute>
<CType>int</CType>
</RtlPorts>
<RtlPorts>
<name>pairs_duration_V_full_n</name>
<Object>pairs_duration_V</Object>
<Type>pointer</Type>
<Scope></Scope>
<IOProtocol>ap_fifo</IOProtocol>
<IOConfig></IOConfig>
<Dir>in</Dir>
<Bits>1</Bits>
<Attribute>control</Attribute>
<CType>int</CType>
</RtlPorts>
<RtlPorts>
<name>pairs_duration_V_write</name>
<Object>pairs_duration_V</Object>
<Type>pointer</Type>
<Scope></Scope>
<IOProtocol>ap_fifo</IOProtocol>
<IOConfig></IOConfig>
<Dir>out</Dir>
<Bits>1</Bits>
<Attribute>control</Attribute>
<CType>int</CType>
</RtlPorts>
</InterfaceSummary>
</Module>
</ModuleInformation>

</profile>
